pyAPMT/__init__.py
pyAPMT/Geostatistics/AdjustVarMod3D.py
pyAPMT/Geostatistics/Capping_Analysis.py
pyAPMT/Geostatistics/Contact_Analysis.py
pyAPMT/Geostatistics/Drill_Holes.py
pyAPMT/Geostatistics/Nearest_Neighbor.py
pyAPMT/Geostatistics/Probability_plots.py
pyAPMT/Geostatistics/Slides_2D.py
pyAPMT/Geostatistics/Variogram_Maps3D.py
pyAPMT/Geostatistics/__init__.py
pyAPMT-0.0.10.data/scripts/AdjustVarMod3D.py
pyAPMT-0.0.10.data/scripts/Capping_Analysis.py
pyAPMT-0.0.10.data/scripts/Contact_Analysis.py
pyAPMT-0.0.10.data/scripts/Drill_Holes.py
pyAPMT-0.0.10.data/scripts/Nearest_Neighbor.py
pyAPMT-0.0.10.data/scripts/Probability_plots.py
pyAPMT-0.0.10.data/scripts/Slides_2D.py
pyAPMT-0.0.10.data/scripts/Variogram_Maps3D.py
pyAPMT-0.0.10.dist-info/LICENSE
pyAPMT-0.0.10.dist-info/METADATA
pyAPMT-0.0.10.dist-info/WHEEL
pyAPMT-0.0.10.dist-info/top_level.txt
pyAPMT-0.0.10.dist-info/RECORD
