Metadata-Version: 2.1
Name: pyAPMT
Version: 0.0.10
Summary: Python package for Mining projects
Home-page: UNKNOWN
Author: Sebastian Avalos
Author-email: sebastian.avalos@apmodtech.com
License: MIT
Keywords: pyAPMT,Mining,Geometallurgy,Geostatistics,Mine planning
Platform: UNKNOWN
Classifier: Programming Language :: Python :: 3
Classifier: License :: OSI Approved :: MIT License
Classifier: Operating System :: OS Independent
License-File: LICENSE
Requires-Dist: requests
Requires-Dist: importlib ; python_version >= "3.6"
